{
  "Material": "AgPb18SbSe19.928Cl0.072",
  "DOIs_Researched": [
    "10.1016/j.nanoen.2013.09.009"
  ],
  "Data_By_Temperature": {
    "873.0": [
      {
        "Original_Name_In_Paper": "n-type AgPb18SbSe19.928Cl0.072",
        "Property": "ZT",
        "Value": 1.3,
        "Units": null,
        "Editing": null,
        "Source_DOI": "10.1016/j.nanoen.2013.09.009"
      },
      {
        "Original_Name_In_Paper": "n-type AgPb18SbSe19.928Cl0.072",
        "Property": "ZT",
        "Value": 1.3,
        "Units": null,
        "Editing": null,
        "Source_DOI": "10.1016/j.nanoen.2013.09.009"
      },
      {
        "Original_Name_In_Paper": "AgPb18SbSe19.928Cl0.072",
        "Property": "ZT",
        "Value": 1.3,
        "Units": null,
        "Editing": null,
        "Source_DOI": "10.1016/j.nanoen.2013.09.009"
      },
      {
        "Original_Name_In_Paper": "AgPb18SbSe19.928Cl0.072",
        "Property": "ZT",
        "Value": 1.3,
        "Units": null,
        "Editing": null,
        "Source_DOI": "10.1016/j.nanoen.2013.09.009"
      },
      {
        "Original_Name_In_Paper": "AgPb18SbSe19.928Cl0.072",
        "Property": "ZT",
        "Value": 1.3,
        "Units": null,
        "Editing": null,
        "Source_DOI": "10.1016/j.nanoen.2013.09.009"
      }
    ]
  }
}