{
  "Material": "SnBi",
  "DOIs_Researched": [
    "10.1016/j.nanoen.2019.104283"
  ],
  "Data_By_Temperature": {
    "300.0": [
      {
        "Original_Name_In_Paper": "Sn2Bi",
        "Property": "ThermCond",
        "Value": 0.19,
        "Units": "Kelvin^(-1.0)  Meter^(-1.0)  Watt^(1.0)",
        "Editing": null,
        "Source_DOI": "10.1016/j.nanoen.2019.104283"
      },
      {
        "Original_Name_In_Paper": "Sn2Bi",
        "Property": "ZT",
        "Value": 2.45,
        "Units": null,
        "Editing": null,
        "Source_DOI": "10.1016/j.nanoen.2019.104283"
      }
    ]
  }
}