{
  "doi": "10.1016/j.nanoen.2020.104658",
  "extraction_status": "success",
  "extracted_data": {
    "material_composition": {
      "materials": [
        "Cu3Sb0.91Hf0.06Sn0.03Se4"
      ]
    },
    "seebeck_coefficient": {
      "seebeck_data": []
    },
    "electrical_conductivity": {
      "conductivity_data": []
    },
    "thermal_conductivity": {
      "thermal_conductivity_data": []
    },
    "power_factor": {
      "power_factor_data": [
        {
          "material": "Cu3Sb0.91Hf0.06Sn0.03Se4",
          "value": 0.001008,
          "unit": "Kelvin^(-2.0)  Meter^(-1.0)  Watt^(1.0)",
          "temperature": "623.0 K"
        }
      ]
    },
    "figure_of_merit_ZT": {
      "zt_data": [
        {
          "material": "Cu3Sb0.91Hf0.06Sn0.03Se4",
          "zt_value": 0.8200000000000001,
          "temperature": "623.0 K"
        }
      ]
    },
    "temperature": {
      "temperature_data": []
    },
    "crystal_structure": {
      "crystal_data": []
    },
    "space_group": {
      "space_group_data": []
    },
    "lattice_parameters": {
      "lattice_data": []
    }
  }
}