{
  "doi": "10.1016/j.cej.2020.127795",
  "extraction_status": "success",
  "extracted_data": {
    "material_composition": {
      "materials": [
        "Sn0.90Mn0.07Bi0.03Te"
      ]
    },
    "seebeck_coefficient": {
      "seebeck_data": []
    },
    "electrical_conductivity": {
      "conductivity_data": []
    },
    "thermal_conductivity": {
      "thermal_conductivity_data": [
        {
          "material": "Sn0.90Mn0.07Bi0.03Te",
          "value": 0.67,
          "unit": "Kelvin^(-1.0)  Meter^(-1.0)  Watt^(1.0)",
          "temperature": "850.0 K"
        }
      ]
    },
    "power_factor": {
      "power_factor_data": [
        {
          "material": "Sn0.90Mn0.07Bi0.03Te",
          "value": 0.00205,
          "unit": "Kelvin^(-2.0)  Meter^(-1.0)  Watt^(1.0)",
          "temperature": "850.0 K"
        }
      ]
    },
    "figure_of_merit_ZT": {
      "zt_data": [
        {
          "material": "Sn0.90Mn0.07Bi0.03Te",
          "zt_value": 1.3,
          "temperature": "850.0 K"
        }
      ]
    },
    "temperature": {
      "temperature_data": []
    },
    "crystal_structure": {
      "crystal_data": []
    },
    "space_group": {
      "space_group_data": []
    },
    "lattice_parameters": {
      "lattice_data": []
    }
  }
}