{
  "doi": "10.1016/j.ceramint.2017.09.143",
  "extraction_status": "success",
  "extracted_data": {
    "material_composition": {
      "materials": [
        "Bi0.82Mg0.09Pb0.09CuSeO"
      ]
    },
    "seebeck_coefficient": {
      "seebeck_data": [
        {
          "material": "Bi0.82Mg0.09Pb0.09CuSeO",
          "value": 0.000084,
          "unit": "Kelvin^(-1.0)  Volt^(1.0)",
          "temperature": "300.0 K"
        }
      ]
    },
    "electrical_conductivity": {
      "conductivity_data": [
        {
          "material": "Bi0.82Mg0.09Pb0.09CuSeO",
          "value": 134690,
          "unit": "Meter^(-1.0)  Siemens^(1.0)",
          "temperature": "300.0 K"
        }
      ]
    },
    "thermal_conductivity": {
      "thermal_conductivity_data": [
        {
          "material": "Bi0.82Mg0.09Pb0.09CuSeO",
          "value": 1.3,
          "unit": "Kelvin^(-1.0)  Meter^(-1.0)  Watt^(1.0)",
          "temperature": "300.0 K"
        },
        {
          "material": "Bi0.82Mg0.09Pb0.09CuSeO",
          "value": 0.07,
          "unit": "Kelvin^(-1.0)  Meter^(-1.0)  Watt^(1.0)",
          "temperature": "750.0 K"
        }
      ]
    },
    "power_factor": {
      "power_factor_data": []
    },
    "figure_of_merit_ZT": {
      "zt_data": []
    },
    "temperature": {
      "temperature_data": []
    },
    "crystal_structure": {
      "crystal_data": []
    },
    "space_group": {
      "space_group_data": []
    },
    "lattice_parameters": {
      "lattice_data": []
    }
  }
}