{
  "doi": "10.1039/c9cc00926d",
  "extraction_status": "success",
  "extracted_data": {
    "material_composition": {
      "materials": [
        "Sr2FeMoO6"
      ]
    },
    "seebeck_coefficient": {
      "seebeck_data": [
        {
          "material": "Sr2FeMoO6",
          "value": -0.000047,
          "unit": "Kelvin^(-1.0)  Volt^(1.0)",
          "temperature": "660.0 K"
        }
      ]
    },
    "electrical_conductivity": {
      "conductivity_data": [
        {
          "material": "Sr2FeMoO6",
          "value": 30600,
          "unit": "Meter^(-1.0)  Siemens^(1.0)",
          "temperature": "1073.0 K"
        }
      ]
    },
    "thermal_conductivity": {
      "thermal_conductivity_data": []
    },
    "power_factor": {
      "power_factor_data": []
    },
    "figure_of_merit_ZT": {
      "zt_data": [
        {
          "material": "Sr2FeMoO6",
          "zt_value": 0.30000000000000004,
          "temperature": "1100.0 K"
        }
      ]
    },
    "temperature": {
      "temperature_data": []
    },
    "crystal_structure": {
      "crystal_data": []
    },
    "space_group": {
      "space_group_data": []
    },
    "lattice_parameters": {
      "lattice_data": []
    }
  }
}