{
  "doi": "10.1016/j.jallcom.2004.07.074",
  "extraction_status": "success",
  "extracted_data": {
    "material_composition": {
      "materials": [
        "TiCo0.9Ni0.1Sb",
        "TiCo0.95Ni0.05Sb"
      ]
    },
    "seebeck_coefficient": {
      "seebeck_data": []
    },
    "electrical_conductivity": {
      "conductivity_data": [
        {
          "material": "TiCo0.9Ni0.1Sb",
          "value": 100000,
          "unit": "Meter^(-1.0)  Siemens^(1.0)",
          "temperature": "295 K"
        }
      ]
    },
    "thermal_conductivity": {
      "thermal_conductivity_data": []
    },
    "power_factor": {
      "power_factor_data": [
        {
          "material": "TiCo0.95Ni0.05Sb",
          "value": 0.0016,
          "unit": "Kelvin^(-2.0)  Meter^(-1.0)  Watt^(1.0)",
          "temperature": "900.0 K"
        },
        {
          "material": "TiCo0.95Ni0.05Sb",
          "value": 0.0016,
          "unit": "Kelvin^(-2.0)  Meter^(-1.0)  Watt^(1.0)",
          "temperature": "750.0 K"
        }
      ]
    },
    "figure_of_merit_ZT": {
      "zt_data": [
        {
          "material": "TiCo0.95Ni0.05Sb",
          "zt_value": 0.27,
          "temperature": "900.0 K"
        },
        {
          "material": "TiCo0.95Ni0.05Sb",
          "zt_value": 0.27,
          "temperature": "900.0 K"
        },
        {
          "material": "TiCo0.95Ni0.05Sb",
          "zt_value": 0.27,
          "temperature": "900.0 K"
        }
      ]
    },
    "temperature": {
      "temperature_data": []
    },
    "crystal_structure": {
      "crystal_data": []
    },
    "space_group": {
      "space_group_data": []
    },
    "lattice_parameters": {
      "lattice_data": []
    }
  }
}